{
  "users": [
    {
      "email": "Brady@test.com",
      "name": "Brady Williams",
      "id": 1
    },
    {
      "email": "colby@test.com",
      "name": "Colby Ryan",
      "id": 2
    },
    {
      "email": "sarah@test.com",
      "name": "Sarah Holcomb",
      "id": 3
    }
  ],
  "vehicles": [
    {
      "id": 1,
      "year": "1990",
      "make": "Nissan",
      "model": "240sx",
      "userId": 1
    },
    {
      "year": "2003",
      "make": "Nissan",
      "model": "350z",
      "userId": 1,
      "id": 3
    },
    {
      "year": "2010",
      "make": "Chevrolet",
      "model": "Terry Cruze",
      "userId": 3,
      "id": 4
    }
  ],
  "tasks": [],
  "events": [
    {
      "id": 3,
      "vehicleId": "1",
      "eventName": "DriftIndy Halloween Bash",
      "eventDesc": "Halloween Event by DriftIndy",
      "eventDate": "2021-10-30",
      "eventTrack": "Indianapolis Motor Speedway"
    },
    {
      "id": 4,
      "vehicleId": "3",
      "eventName": "Test",
      "eventDesc": "Test",
      "eventDate": "2021-11-02",
      "eventTrack": "test"
    }
  ],
  "photos": []
}